ipify/__init__.py
ipify/exceptions.py
ipify/ipify.py
ipify/settings.py
ipify_py-1.0.1.dist-info/METADATA
ipify_py-1.0.1.dist-info/WHEEL
ipify_py-1.0.1.dist-info/top_level.txt
ipify_py-1.0.1.dist-info/RECORD
